README.rst
setup.cfg
setup.py
ruminaq/Engine.py
ruminaq/Globals.py
ruminaq/InputPort.py
ruminaq/Logger.py
ruminaq/OutputPort.py
ruminaq/PythonTask.py
ruminaq/PythonTaskListener.py
ruminaq/__init__.py
ruminaq/parameter.py
ruminaq/python_task_info.py
ruminaq.egg-info/PKG-INFO
ruminaq.egg-info/SOURCES.txt
ruminaq.egg-info/dependency_links.txt
ruminaq.egg-info/requires.txt
ruminaq.egg-info/top_level.txt
ruminaq/data/Bool.py
ruminaq/data/Complex32.py
ruminaq/data/Complex64.py
ruminaq/data/Control.py
ruminaq/data/Data.py
ruminaq/data/Decimal.py
ruminaq/data/Float32.py
ruminaq/data/Float64.py
ruminaq/data/Int32.py
ruminaq/data/Int64.py
ruminaq/data/Raw.py
ruminaq/data/Text.py
ruminaq/data/__init__.py
ruminaq/test/__init__.py
ruminaq/test/test_ruminaq.py