Metadata-Version: 1.0
Name: ruminaq
Version: 1.0.2
Summary: python task api
Home-page: UNKNOWN
Author: Marek Jagielski
Author-email: marek.jagielski@gmail.com
License: Apache License version 2.0
Platform: UNKNOWN
